dander/__about__.py
dander/__init__.py
dander/cli.py
dander/_dbt/__init__.py
dander/io/__init__.py
dander/io/json_utils.py
dander/io/xml_utils.py
dander-0.4.0.dist-info/METADATA
dander-0.4.0.dist-info/WHEEL
dander-0.4.0.dist-info/entry_points.txt
dander-0.4.0.dist-info/licenses/LICENSE
dander-0.4.0.dist-info/licenses/LICENSE.txt
dander-0.4.0.dist-info/RECORD
