Metadata-Version: 2.4
Name: dander
Version: 0.4.0
Summary: Data Analytics & Data Engineering Resources
Project-URL: Documentation, https://github.com/danlsn/dander#readme
Project-URL: Issues, https://github.com/danlsn/dander/issues
Project-URL: Source, https://github.com/danlsn/dander
Author-email: Daniel Lawson <52593003+danlsn@users.noreply.github.com>
License-Expression: MIT
License-File: LICENSE
License-File: LICENSE.txt
Classifier: Development Status :: 4 - Beta
Classifier: Programming Language :: Python
Classifier: Programming Language :: Python :: 3.8
Classifier: Programming Language :: Python :: 3.9
Classifier: Programming Language :: Python :: 3.10
Classifier: Programming Language :: Python :: 3.11
Classifier: Programming Language :: Python :: 3.12
Classifier: Programming Language :: Python :: Implementation :: CPython
Classifier: Programming Language :: Python :: Implementation :: PyPy
Requires-Python: >=3.8
Requires-Dist: loguru
Requires-Dist: pyperclip>=1.9.0
Requires-Dist: rich
Requires-Dist: typer
Provides-Extra: dbt
Requires-Dist: dbt-core; extra == 'dbt'
Provides-Extra: dev
Requires-Dist: black; extra == 'dev'
